Workbook

Sheet Model
C2: Yearly Expenses (post tax, today's $) | E2: =8000*2*12 -> 192000
C3: This Year | E3: 2024
C4: Retirement Age | E4: 65
C5: Life Expectancy | E5: 105
C6: Retirement Year (start) | E6: =E3+E4-50 -> 2039
C7: Planned retirement years | E7: =E5-E4+1 -> 41
C8: 401(k) | E8: 2818215
C9: Current Post tax Assets | E9: =3850000-E8 -> 1031785
D11: Average | E11: SD
C12: Inflation | D12: 0.037 | E12: 0.028
C13: Return | D13: 0.0951 | E13: 0.0704
A15: Age | B15: Beginning of Year | C15: Income | D15: Draw from Assets | E15: Draw from 401(k) | F15: Remaining Asset | G15: Post-tax assets | H15: 401(k) | I15: Tax rate | J15: Normal return | K15: Adj. Return | L15: Est. yearly retirement Expenses (net of income) | M15: Inflation adjusted annual retirement expenses | N15: Inflation
A16: 50 | B16: =E3 -> 2024 | D16: =IF(L16 = 0, 0, TRUNC(L16-C16-E16*(1-I16))) -> 0 | E16: =IF(L16=0,-22500,IF((L16-C16)/(1-I16)>=H15,H15,(L16-C16)/(1-I16))) -> -22500 | F16: =G16+H16 -> 3850000 | G16: =E9 -> 1031785 | H16: =E8 -> 2818215 | I16: =37%+5.6% -> 0.426 | J16: =Actuals!E5 -> 0.18993098 | K16: =J16 -> 0.18993098 | L16: =IF(B16>=$E$6, M16-C16, 0) -> 0 | M16: =E2 -> 192000 | N16: =_xlfn.NORM.INV(RAND(),$D$12,$E$12) -> 0.028002241
A17: 51 | B17: =B16+1 -> 2025 | D17: =IF(L17 = 0, 0, TRUNC(L17-C17-E17*(1-I17))) -> 0 | E17: =IF(L17=0,-30500,IF((L17-C17)/(1-I17)>=H16,H16,(L17-C17)/(1-I17))) -> -30500 | F17: =G17+H17 -> 4581234.3 | G17: =Actuals!C5 -> 1351432.2 | H17: =Actuals!D5 -> 3229802 | I17: =37%+5.6% -> 0.426 | J17: =_xlfn.NORM.INV(RAND(),$D$13,$E$13) -> 0.10302414 | K17: =IF(J17>0.2, 0.2, J17) -> 0.10302414 | L17: =IF(B17>=$E$6, M17-C17, 0) -> 0 | M17: =M16*(1+N16) -> 197376.43 | N17: =_xlfn.NORM.INV(RAND(),$D$12,$E$12) -> 0.061352249
A18: 52 | B18: =B17+1 -> 2026 | D18: =IF(L18 = 0, 0, TRUNC(L18-C18-E18*(1-I18))) -> 0 | E18: =IF(L18=0,-30500,IF((L18-C18)/(1-I18)>=H17,H17,(L18-C18)/(1-I18))) -> -30500 | F18: =G18+H18 -> 5086854.2 | G18: =(G17-D18)*(1+K17) -> 1490662.4 | H18: =(H17-E18)*(1+K17) -> 3596191.8 | I18: =37%+5.6% -> 0.426 | J18: =_xlfn.NORM.INV(RAND(),$D$13,$E$13) -> 0.24960825 | K18: =IF(J18>0.2, 0.2, J18) -> 0.2 | L18: =IF(B18>=$E$6, M18-C18, 0) -> 0 | M18: =M17*(1+N17) -> 209485.92 | N18: =_xlfn.NORM.INV(RAND(),$D$12,$E$12) -> 0.040539736
A19: 53 | B19: =B18+1 -> 2027 | D19: =IF(L19 = 0, 0, TRUNC(L19-C19-E19*(1-I19))) -> 0 | E19: =IF(L19=0,-30500,IF((L19-C19)/(1-I19)>=H18,H18,(L19-C19)/(1-I19))) -> -30500 | F19: =G19+H19 -> 6140825.1 | G19: =(G18-D19)*(1+K18) -> 1788794.9 | H19: =(H18-E19)*(1+K18) -> 4352030.2 | I19: =37%+5.6% -> 0.426 | J19: =_xlfn.NORM.INV(RAND(),$D$13,$E$13) -> 0.10430836 | K19: =IF(J19>0.2, 0.2, J19) -> 0.10430836 | L19: =IF(B19>=$E$6, M19-C19, 0) -> 0 | M19: =M18*(1+N18) -> 217978.42 | N19: =_xlfn.NORM.INV(RAND(),$D$12,$E$12) -> 0.01757553
A20: 54 | B20: =B19+1 -> 2028 | D20: =IF(L20 = 0, 0, TRUNC(L20-C20-E20*(1-I20))) -> 0 | E20: =IF(L20=0,-30500,IF((L20-C20)/(1-I20)>=H19,H19,(L20-C20)/(1-I20))) -> -30500 | F20: =G20+H20 -> 6815045.8 | G20: =(G19-D20)*(1+K19) -> 1975381.1 | H20: =(H19-E20)*(1+K19) -> 4839664.7 | I20: =37%+5.6% -> 0.426 | J20: =_xlfn.NORM.INV(RAND(),$D$13,$E$13) -> 0.12740044 | K20: =IF(J20>0.2, 0.2, J20) -> 0.12740044 | L20: =IF(B20>=$E$6, M20-C20, 0) -> 0 | M20: =M19*(1+N19) -> 221809.51 | N20: =_xlfn.NORM.INV(RAND(),$D$12,$E$12) -> 0.026901436
A21: 55 | B21: =B20+1 -> 2029 | D21: =IF(L21 = 0, 0, TRUNC(L21-C21-E21*(1-I21))) -> 0 | E21: =IF(L21=0,-30500,IF((L21-C21)/(1-I21)>=H20,H20,(L21-C21)/(1-I21))) -> -30500 | F21: =G21+H21 -> 7717671.4 | G21: =(G20-D21)*(1+K20) -> 2227045.6 | H21: =(H20-E21)*(1+K20) -> 5490625.9 | I21: =37%+5.6% -> 0.426 | J21: =_xlfn.NORM.INV(RAND(),$D$13,$E$13) -> 0.074708674 | K21: =IF(J21>0.2, 0.2, J21) -> 0.074708674 | L21: =IF(B21>=$E$6, M21-C21, 0) -> 0 | M21: =M20*(1+N20) -> 227776.5 | N21: =_xlfn.NORM.INV(RAND(),$D$12,$E$12) -> 0.056220706
A22: 56 | B22: =B21+1 -> 2030 | D22: =IF(L22 = 0, 0, TRUNC(L22-C22-E22*(1-I22))) -> 0 | E22: =IF(L22=0,-30500,IF((L22-C22)/(1-I22)>=H21,H21,(L22-C22)/(1-I22))) -> -30500 | F22: =G22+H22 -> 8327027 | G22: =(G21-D22)*(1+K21) -> 2393425.2 | H22: =(H21-E22)*(1+K21) -> 5933601.9 | I22: =37%+5.6% -> 0.426 | J22: =_xlfn.NORM.INV(RAND(),$D$13,$E$13) -> 0.095214305 | K22: =IF(J22>0.2, 0.2, J22) -> 0.095214305 | L22: =IF(B22>=$E$6, M22-C22, 0) -> 0 | M22: =M21*(1+N21) -> 240582.26 | N22: =_xlfn.NORM.INV(RAND(),$D$12,$E$12) -> 0.073493364
A23: 57 | B23: =B22+1 -> 2031 | D23: =IF(L23 = 0, 0, TRUNC(L23-C23-E23*(1-I23))) -> 0 | E23: =IF(L23=0,-30500,IF((L23-C23)/(1-I23)>=H22,H22,(L23-C23)/(1-I23))) -> -30500 | F23: =G23+H23 -> 9153283.2 | G23: =(G22-D23)*(1+K22) -> 2621313.5 | H23: =(H22-E23)*(1+K22) -> 6531969.7 | I23: =37%+5.6% -> 0.426 | J23: =_xlfn.NORM.INV(RAND(),$D$13,$E$13) -> 0.1362161 | K23: =IF(J23>0.2, 0.2, J23) -> 0.1362161 | L23: =IF(B23>=$E$6, M23-C23, 0) -> 0 | M23: =M22*(1+N22) -> 258263.46 | N23: =_xlfn.NORM.INV(RAND(),$D$12,$E$12) -> 0.043679387
A24: 58 | B24: =B23+1 -> 2032 | D24: =IF(L24 = 0, 0, TRUNC(L24-C24-E24*(1-I24))) -> 0 | E24: =IF(L24=0,-30500,IF((L24-C24)/(1-I24)>=H23,H23,(L24-C24)/(1-I24))) -> -30500 | F24: =G24+H24 -> 10434762 | G24: =(G23-D24)*(1+K23) -> 2978378.6 | H24: =(H23-E24)*(1+K23) -> 7456383.7 | I24: =37%+5.6% -> 0.426 | J24: =_xlfn.NORM.INV(RAND(),$D$13,$E$13) -> 0.23330039 | K24: =IF(J24>0.2, 0.2, J24) -> 0.2 | L24: =IF(B24>=$E$6, M24-C24, 0) -> 0 | M24: =M23*(1+N23) -> 269544.25 | N24: =_xlfn.NORM.INV(RAND(),$D$12,$E$12) -> 0.071146345
A25: 59 | B25: =B24+1 -> 2033 | D25: =IF(L25 = 0, 0, TRUNC(L25-C25-E25*(1-I25))) -> 0 | E25: =IF(L25=0,-30500,IF((L25-C25)/(1-I25)>=H24,H24,(L25-C25)/(1-I25))) -> -30500 | F25: =G25+H25 -> 12558315 | G25: =(G24-D25)*(1+K24) -> 3574054.3 | H25: =(H24-E25)*(1+K24) -> 8984260.4 | I25: =37%+5.6% -> 0.426 | J25: =_xlfn.NORM.INV(RAND(),$D$13,$E$13) -> 0.20064312 | K25: =IF(J25>0.2, 0.2, J25) -> 0.2 | L25: =IF(B25>=$E$6, M25-C25, 0) -> 0 | M25: =M24*(1+N24) -> 288721.34 | N25: =_xlfn.NORM.INV(RAND(),$D$12,$E$12) -> 0.052360786
A26: 60 | B26: =B25+1 -> 2034 | D26: =IF(L26 = 0, 0, TRUNC(L26-C26-E26*(1-I26))) -> 0 | E26: =IF(L26=0,-30500,IF((L26-C26)/(1-I26)>=H25,H25,(L26-C26)/(1-I26))) -> -30500 | F26: =G26+H26 -> 15106578 | G26: =(G25-D26)*(1+K25) -> 4288865.2 | H26: =(H25-E26)*(1+K25) -> 10817713 | I26: =37%+5.6% -> 0.426 | J26: =_xlfn.NORM.INV(RAND(),$D$13,$E$13) -> 0.13777826 | K26: =IF(J26>0.2, 0.2, J26) -> 0.13777826 | L26: =IF(B26>=$E$6, M26-C26, 0) -> 0 | M26: =M25*(1+N25) -> 303839.01 | N26: =_xlfn.NORM.INV(RAND(),$D$12,$E$12) -> 0.025217314
A27: 61 | B27: =B26+1 -> 2035 | D27: =IF(L27 = 0, 0, TRUNC(L27-C27-E27*(1-I27))) -> 0 | E27: =IF(L27=0,-30500,IF((L27-C27)/(1-I27)>=H26,H26,(L27-C27)/(1-I27))) -> -30500 | F27: =G27+H27 -> 17222638 | G27: =(G26-D27)*(1+K26) -> 4879777.6 | H27: =(H26-E27)*(1+K26) -> 12342860 | I27: =37%+5.6% -> 0.426 | J27: =_xlfn.NORM.INV(RAND(),$D$13,$E$13) -> 0.12444673 | K27: =IF(J27>0.2, 0.2, J27) -> 0.12444673 | L27: =IF(B27>=$E$6, M27-C27, 0) -> 0 | M27: =M26*(1+N26) -> 311501.02 | N27: =_xlfn.NORM.INV(RAND(),$D$12,$E$12) -> 0.04093742
A28: 62 | B28: =B27+1 -> 2036 | D28: =IF(L28 = 0, 0, TRUNC(L28-C28-E28*(1-I28))) -> 0 | E28: =IF(L28=0,-30500,IF((L28-C28)/(1-I28)>=H27,H27,(L28-C28)/(1-I28))) -> -30500 | F28: =G28+H28 -> 19400235 | G28: =(G27-D28)*(1+K27) -> 5487049.9 | H28: =(H27-E28)*(1+K27) -> 13913185 | I28: =37%+5.6% -> 0.426 | J28: =_xlfn.NORM.INV(RAND(),$D$13,$E$13) -> 0.16193003 | K28: =IF(J28>0.2, 0.2, J28) -> 0.16193003 | L28: =IF(B28>=$E$6, M28-C28, 0) -> 0 | M28: =M27*(1+N27) -> 324253.06 | N28: =_xlfn.NORM.INV(RAND(),$D$12,$E$12) -> 0.039831944
A29: 63 | B29: =B28+1 -> 2037 | D29: =IF(L29 = 0, 0, TRUNC(L29-C29-E29*(1-I29))) -> 0 | E29: =IF(L29=0,-30500,IF((L29-C29)/(1-I29)>=H28,H28,(L29-C29)/(1-I29))) -> -30500 | F29: =G29+H29 -> 22577154 | G29: =(G28-D29)*(1+K28) -> 6375568.1 | H29: =(H28-E29)*(1+K28) -> 16201586 | I29: =37%+5.6% -> 0.426 | J29: =_xlfn.NORM.INV(RAND(),$D$13,$E$13) -> 0.10663942 | K29: =IF(J29>0.2, 0.2, J29) -> 0.10663942 | L29: =IF(B29>=$E$6, M29-C29, 0) -> 0 | M29: =M28*(1+N28) -> 337168.69 | N29: =_xlfn.NORM.INV(RAND(),$D$12,$E$12) -> 0.029521716
... A37: 71 | B37: =B36+1 -> 2045 | D37: =IF(L37 = 0, 0, TRUNC(L37-C37-E37*(1-I37))) -> 0 | E37: =IF(L37=0,-30500,IF((L37-C37)/(1-I37)>=H36,H36,(L37-C37)/(1-I37))) -> 676655.67 | F37: =G37+H37 -> 37598798 | G37: =(G36-D37)*(1+K36) -> 12284152 | H37: =(H36-E37)*(1+K36) -> 25314646 | I37: =37%+5.6% -> 0.426 | J37: =_xlfn.NORM.INV(RAND(),$D$13,$E$13) -> 0.12542213 | K37: =IF(J37>0.2, 0.2, J37) -> 0.12542213 | L37: =IF(B37>=$E$6, M37-C37, 0) -> 388400.35 | M37: =M36*(1+N36) -> 388400.35 | N37: =_xlfn.NORM.INV(RAND(),$D$12,$E$12) -> 0.049174633
A38: 72 | B38: =B37+1 -> 2046 | C38: 40000 | D38: =IF(L38 = 0, 0, TRUNC(L38-C38-E38*(1-I38))) -> 0 | E38: =IF(L38=0,-30500,IF((L38-C38)/(1-I38)>=H37,H37,(L38-C38)/(1-I38))) -> 570557.14 | F38: =G38+H38 -> 41672402 | G38: =(G37-D38)*(1+K37) -> 13824856 | H38: =(H37-E38)*(1+K37) -> 27847545 | I38: =37%+5.6% -> 0.426 | J38: =_xlfn.NORM.INV(RAND(),$D$13,$E$13) -> 0.077886125 | K38: =IF(J38>0.2, 0.2, J38) -> 0.077886125 | L38: =IF(B38>=$E$6, M38-C38, 0) -> 367499.8 | M38: =M37*(1+N37) -> 407499.8 | N38: =_xlfn.NORM.INV(RAND(),$D$12,$E$12) -> 0.039065701
A39: 73 | B39: =B38+1 -> 2047 | C39: 40000 | D39: =IF(L39 = 0, 0, TRUNC(L39-C39-E39*(1-I39))) -> 0 | E39: =IF(L39=0,-30500,IF((L39-C39)/(1-I39)>=H38,H38,(L39-C39)/(1-I39))) -> 598291.05 | F39: =G39+H39 -> 44273214 | G39: =(G38-D39)*(1+K38) -> 14901621 | H39: =(H38-E39)*(1+K38) -> 29371593 | I39: =37%+5.6% -> 0.426 | J39: =_xlfn.NORM.INV(RAND(),$D$13,$E$13) -> 0.062026676 | K39: =IF(J39>0.2, 0.2, J39) -> 0.062026676 | L39: =IF(B39>=$E$6, M39-C39, 0) -> 383419.06 | M39: =M38*(1+N38) -> 423419.06 | N39: =_xlfn.NORM.INV(RAND(),$D$12,$E$12) -> 0.026447203
A40: 74 | B40: =B39+1 -> 2048 | C40: 40000 | D40: =IF(L40 = 0, 0, TRUNC(L40-C40-E40*(1-I40))) -> 0 | E40: =IF(L40=0,-30500,IF((L40-C40)/(1-I40)>=H39,H39,(L40-C40)/(1-I40))) -> 617800.2 | F40: =G40+H40 -> 46363214 | G40: =(G39-D40)*(1+K39) -> 15825919 | H40: =(H39-E40)*(1+K39) -> 30537295 | I40: =37%+5.6% -> 0.426 | J40: =_xlfn.NORM.INV(RAND(),$D$13,$E$13) -> 0.082578353 | K40: =IF(J40>0.2, 0.2, J40) -> 0.082578353 | L40: =IF(B40>=$E$6, M40-C40, 0) -> 394617.31 | M40: =M39*(1+N39) -> 434617.31 | N40: =_xlfn.NORM.INV(RAND(),$D$12,$E$12) -> 0.0029092602
A41: 75 | B41: =B40+1 -> 2049 | C41: 40000 | D41: =IF(L41 = 0, 0, TRUNC(L41-C41-E41*(1-I41))) -> 0 | E41: =IF(L41=0,-30500,IF((L41-C41)/(1-I41)>=H40,H40,(L41-C41)/(1-I41))) -> 620003.01 | F41: =G41+H41 -> 49520610 | G41: =(G40-D41)*(1+K40) -> 17132797 | H41: =(H40-E41)*(1+K40) -> 32387812 | I41: =37%+5.6% -> 0.426 | J41: =_xlfn.NORM.INV(RAND(),$D$13,$E$13) -> 0.10898502 | K41: =IF(J41>0.2, 0.2, J41) -> 0.10898502 | L41: =IF(B41>=$E$6, M41-C41, 0) -> 395881.73 | M41: =M40*(1+N40) -> 435881.73 | N41: =_xlfn.NORM.INV(RAND(),$D$12,$E$12) -> 0.054065028
A42: 76 | B42: =B41+1 -> 2050 | C42: 40000 | D42: =IF(L42 = 0, 0, TRUNC(L42-C42-E42*(1-I42))) -> 0 | E42: =IF(L42=0,-30500,IF((L42-C42)/(1-I42)>=H41,H41,(L42-C42)/(1-I42))) -> 661058.69 | F42: =G42+H42 -> 54184510 | G42: =(G41-D42)*(1+K41) -> 19000016 | H42: =(H41-E42)*(1+K41) -> 35184495 | I42: =37%+5.6% -> 0.426 | J42: =_xlfn.NORM.INV(RAND(),$D$13,$E$13) -> 0.10211824 | K42: =IF(J42>0.2, 0.2, J42) -> 0.10211824 | L42: =IF(B42>=$E$6, M42-C42, 0) -> 419447.69 | M42: =M41*(1+N41) -> 459447.69 | N42: =_xlfn.NORM.INV(RAND(),$D$12,$E$12) -> 0.071611381
A43: 77 | B43: =B42+1 -> 2051 | C43: 40000 | D43: =IF(L43 = 0, 0, TRUNC(L43-C43-E43*(1-I43))) -> 0 | E43: =IF(L43=0,-30500,IF((L43-C43)/(1-I43)>=H42,H42,(L43-C43)/(1-I43))) -> 718378.7 | F43: =G43+H43 -> 58925999 | G43: =(G42-D43)*(1+K42) -> 20940264 | H43: =(H42-E43)*(1+K42) -> 37985735 | I43: =37%+5.6% -> 0.426 | J43: =_xlfn.NORM.INV(RAND(),$D$13,$E$13) -> 0.092151722 | K43: =IF(J43>0.2, 0.2, J43) -> 0.092151722 | L43: =IF(B43>=$E$6, M43-C43, 0) -> 452349.37 | M43: =M42*(1+N42) -> 492349.37 | N43: =_xlfn.NORM.INV(RAND(),$D$12,$E$12) -> 0.0092130388
A44: 78 | B44: =B43+1 -> 2052 | C44: 40000 | D44: =IF(L44 = 0, 0, TRUNC(L44-C44-E44*(1-I44))) -> 0 | E44: =IF(L44=0,-30500,IF((L44-C44)/(1-I44)>=H43,H43,(L44-C44)/(1-I44))) -> 726281.19 | F44: =G44+H44 -> 63562922 | G44: =(G43-D44)*(1+K43) -> 22869945 | H44: =(H43-E44)*(1+K43) -> 40692977 | I44: =37%+5.6% -> 0.426 | J44: =_xlfn.NORM.INV(RAND(),$D$13,$E$13) -> 0.088884695 | K44: =IF(J44>0.2, 0.2, J44) -> 0.088884695 | L44: =IF(B44>=$E$6, M44-C44, 0) -> 456885.41 | M44: =M43*(1+N43) -> 496885.41 | N44: =_xlfn.NORM.INV(RAND(),$D$12,$E$12) -> -0.0017918612
A45: 79 | B45: =B44+1 -> 2053 | C45: 40000 | D45: =IF(L45 = 0, 0, TRUNC(L45-C45-E45*(1-I45))) -> 0 | E45: =IF(L45=0,-30500,IF((L45-C45)/(1-I45)>=H44,H44,(L45-C45)/(1-I45))) -> 724730.06 | F45: =G45+H45 -> 68423545 | G45: =(G44-D45)*(1+K44) -> 24902733 | H45: =(H44-E45)*(1+K44) -> 43520812 | I45: =37%+5.6% -> 0.426 | J45: =_xlfn.NORM.INV(RAND(),$D$13,$E$13) -> 0.058284568 | K45: =IF(J45>0.2, 0.2, J45) -> 0.058284568 | L45: =IF(B45>=$E$6, M45-C45, 0) -> 455995.06 | M45: =M44*(1+N44) -> 495995.06 | N45: =_xlfn.NORM.INV(RAND(),$D$12,$E$12) -> 0.02061403
A46: 80 | B46: =B45+1 -> 2054 | C46: 40000 | D46: =IF(L46 = 0, 0, TRUNC(L46-C46-E46*(1-I46))) -> 0 | E46: =IF(L46=0,-30500,IF((L46-C46)/(1-I46)>=H45,H45,(L46-C46)/(1-I46))) -> 742542.7 | F46: =G46+H46 -> 71625761 | G46: =(G45-D46)*(1+K45) -> 26354178 | H46: =(H45-E46)*(1+K45) -> 45271582 | I46: =37%+5.6% -> 0.426 | J46: =_xlfn.NORM.INV(RAND(),$D$13,$E$13) -> 0.11744899 | K46: =IF(J46>0.2, 0.2, J46) -> 0.11744899 | L46: =IF(B46>=$E$6, M46-C46, 0) -> 466219.51 | M46: =M45*(1+N45) -> 506219.51 | N46: =_xlfn.NORM.INV(RAND(),$D$12,$E$12) -> 0.077139441
A47: 81 | B47: =B46+1 -> 2055 | C47: 40000 | D47: =IF(L47 = 0, 0, TRUNC(L47-C47-E47*(1-I47))) -> 0 | E47: =IF(L47=0,-30500,IF((L47-C47)/(1-I47)>=H46,H46,(L47-C47)/(1-I47))) -> 810573.18 | F47: =G47+H47 -> 79132360 | G47: =(G46-D47)*(1+K46) -> 29449450 | H47: =(H46-E47)*(1+K46) -> 49682910 | I47: =37%+5.6% -> 0.426 | J47: =_xlfn.NORM.INV(RAND(),$D$13,$E$13) -> 0.16042769 | K47: =IF(J47>0.2, 0.2, J47) -> 0.16042769 | L47: =IF(B47>=$E$6, M47-C47, 0) -> 505269 | M47: =M46*(1+N46) -> 545269 | N47: =_xlfn.NORM.INV(RAND(),$D$12,$E$12) -> 0.10533152
A48: 82 | B48: =B47+1 -> 2056 | C48: 40000 | D48: =IF(L48 = 0, 0, TRUNC(L48-C48-E48*(1-I48))) -> 0 | E48: =IF(L48=0,-30500,IF((L48-C48)/(1-I48)>=H47,H47,(L48-C48)/(1-I48))) -> 910632.43 | F48: =G48+H48 -> 90770658 | G48: =(G47-D48)*(1+K47) -> 34173957 | H48: =(H47-E48)*(1+K47) -> 56596701 | I48: =37%+5.6% -> 0.426 | J48: =_xlfn.NORM.INV(RAND(),$D$13,$E$13) -> 0.10964345 | K48: =IF(J48>0.2, 0.2, J48) -> 0.10964345 | L48: =IF(B48>=$E$6, M48-C48, 0) -> 562703.02 | M48: =M47*(1+N47) -> 602703.02 | N48: =_xlfn.NORM.INV(RAND(),$D$12,$E$12) -> -0.00034964715
A49: 83 | B49: =B48+1 -> 2057 | C49: 40000 | D49: =IF(L49 = 0, 0, TRUNC(L49-C49-E49*(1-I49))) -> 0 | E49: =IF(L49=0,-30500,IF((L49-C49)/(1-I49)>=H48,H48,(L49-C49)/(1-I49))) -> 910265.3 | F49: =G49+H49 -> 99712997 | G49: =(G48-D49)*(1+K48) -> 37920908 | H49: =(H48-E49)*(1+K48) -> 61792089 | I49: =37%+5.6% -> 0.426 | J49: =_xlfn.NORM.INV(RAND(),$D$13,$E$13) -> -0.01758327 | K49: =IF(J49>0.2, 0.2, J49) -> -0.01758327 | L49: =IF(B49>=$E$6, M49-C49, 0) -> 562492.28 | M49: =M48*(1+N48) -> 602492.28 | N49: =_xlfn.NORM.INV(RAND(),$D$12,$E$12) -> 0.040993537
... A71: 105 | B71: =B70+1 -> 2079 | C71: 40000 | D71: =IF(L71 = 0, 0, TRUNC(L71-C71-E71*(1-I71))) -> 0 | E71: =IF(L71=0,-30500,IF((L71-C71)/(1-I71)>=H70,H70,(L71-C71)/(1-I71))) -> 2086552.7 | F71: =G71+H71 -> 7.6704379e+08 | G71: =(G70-D71)*(1+K70) -> 3.3478964e+08 | H71: =(H70-E71)*(1+K70) -> 4.3225415e+08 | I71: =37%+5.6% -> 0.426 | J71: =_xlfn.NORM.INV(RAND(),$D$13,$E$13) -> 0.14006416 | K71: =IF(J71>0.2, 0.2, J71) -> 0.14006416 | L71: =IF(B71>=$E$6, M71-C71, 0) -> 1237681.3 | M71: =M70*(1+N70) -> 1277681.3 | N71: =_xlfn.NORM.INV(RAND(),$D$12,$E$12) -> 0.030473567

Sheet Actuals
A2: Actuals
A3: Year | B3: Date | C3: Regular Assets | D3: 401(k) Assets | E3: % change | F3: Annualized Rate of Return | G3: S&P 500 | H3: S&P Return (ann. Same period)
B4: 45383 | C4: 1031785 | D4: 2818215 | G4: 5254.35
A5: 2025 | B5: 45658 | C5: =4581234.27-D5 -> 1351432.2 | D5: 3229802 | E5: =(D5+C5)/(D4+C4) - 1 -> 0.18993098 | F5: =(1+ E5)^(4/3) - 1 -> 0.2609437 | G5: 5881.63 | H5: =(G5/G4)^(4/3) - 1 -> 0.1622644
B6: 45748 | C6: =119524.28+412699.29+832100.64 -> 1364324.2 | D6: =4753081.42-C6 -> 3388757.2 | E6: =(D6+C6)/(D5+C5) - 1 -> 0.037511103 | F6: =(1+E6)^4 - 1 -> 0.15870001 | G6: 5611.85 | H6: =(G6/G5)^4 - 1 -> -0.17123116

Sheet Asset Simulation
B1: 2024 | C1: 2034 | D1: 2044 | E1: 2054 | F1: 2064 | G1: 2074 | H1: 2079
B2: 50 | C2: =B2+C1-B1 -> 60 | D2: =C2+D1-C1 -> 70 | E2: =D2+E1-D1 -> 80 | F2: =E2+F1-E1 -> 90 | G2: =F2+G1-F1 -> 100 | H2: =G2+H1-G1 -> 105
A3: Prob. have money | B3: =COUNTIF(B7:B10006, ">0")/10000 -> 1 | C3: =COUNTIF(C7:C10006, ">0")/10000 -> 1 | D3: =COUNTIF(D7:D10006, ">0")/10000 -> 1 | E3: =COUNTIF(E7:E10006, ">0")/10000 -> 1 | F3: =COUNTIF(F7:F10006, ">0")/10000 -> 0.9969 | G3: =COUNTIF(G7:G10006, ">0")/10000 -> 0.9865 | H3: =COUNTIF(H7:H10006, ">0")/10000 -> 0.9804
A4: Average Remaining Assets | B4: =AVERAGE(B7:B10006) -> 3850000 | C4: =AVERAGE(C7:C10006) -> 10620420 | D4: =AVERAGE(D7:D10006) -> 20972277 | E4: =AVERAGE(E7:E10006) -> 39158450 | F4: =AVERAGE(F7:F10006) -> 78159470 | G4: =AVERAGE(G7:G10006) -> 1.6602334e+08 | H4: =AVERAGE(H7:H10006) -> 2.4703088e+08
B6: =Model!F16 -> 3850000 | C6: =Model!F26 -> 15106578 | D6: =Model!F36 -> 36242650 | E6: =Model!F46 -> 71625761 | F6: =Model!F56 -> 1.9236649e+08 | G6: =Model!F66 -> 4.3013281e+08 | H6: =Model!F71 -> 7.6704379e+08
A7: 1 | B7: 3850000 | C7: 9911562.7 | D7: 15847348 | E7: 20765527 | F7: 31538506 | G7: 57949435 | H7: 69550581
A8: 2 | B8: 3850000 | C8: 10114128 | D8: 23308649 | E8: 24080597 | F8: 56856706 | G8: 95705462 | H8: 1.2463446e+08
A9: 3 | B9: 3850000 | C9: 10696987 | D9: 14027604 | E9: 15593159 | F9: 21248711 | G9: 40365959 | H9: 48900695
A10: 4 | B10: 3850000 | C10: 14903835 | D10: 29864982 | E10: 65238331 | F10: 1.5211451e+08 | G10: 3.4734762e+08 | H10: 4.8707993e+08
A11: 5 | B11: 3850000 | C11: 11909990 | D11: 27581861 | E11: 45411732 | F11: 73028938 | G11: 2.2280308e+08 | H11: 3.5194585e+08
A12: 6 | B12: 3850000 | C12: 11427184 | D12: 25478155 | E12: 55672153 | F12: 1.1214566e+08 | G12: 3.2158045e+08 | H12: 4.8759602e+08
A13: 7 | B13: 3850000 | C13: 10196699 | D13: 22090463 | E13: 37318819 | F13: 72717757 | G13: 1.6154076e+08 | H13: 2.7336428e+08
A14: 8 | B14: 3850000 | C14: 8612448.9 | D14: 18092821 | E14: 47248641 | F14: 1.2003217e+08 | G14: 2.9623906e+08 | H14: 3.9092756e+08
A15: 9 | B15: 3850000 | C15: 12331747 | D15: 14667298 | E15: 29722646 | F15: 60408966 | G15: 91428119 | H15: 1.6346476e+08
A16: 10 | B16: 3850000 | C16: 8068170.8 | D16: 20474559 | E16: 25312629 | F16: 40477241 | G16: 83173636 | H16: 1.1368682e+08
A17: 11 | B17: 3850000 | C17: 7629906.9 | D17: 13288968 | E17: 21854214 | F17: 34852706 | G17: 60269049 | H17: 1.0211457e+08
A18: 12 | B18: 3850000 | C18: 11248470 | D18: 21046259 | E18: 37125048 | F18: 89349333 | G18: 2.5575366e+08 | H18: 3.9597103e+08
... A10006: 10000 | B10006: 3850000 | C10006: 9940976.2 | D10006: 16123734 | E10006: 34884004 | F10006: 82415614 | G10006: 1.528207e+08 | H10006: 3.0607249e+08

Sheet Sheet3
A1: Year | B1: Jan | C1: Feb | D1: Mar | E1: Apr | F1: May | G1: Jun | H1: Jul | I1: Aug | J1: Sep | K1: Oct | L1: Nov | M1: Dec | N1: Ave
A2: 1914 | B2: 2 | C2: 1 | D2: 1 | E2: 0 | F2: 2.1 | G2: 1 | H2: 1 | I2: 3 | J2: 2 | K2: 1 | L2: 1 | M2: 1 | N2: 1
A3: 1915 | B3: 1 | C3: 1 | D3: 0 | E3: 2 | F3: 2 | G3: 2 | H3: 1 | I3: -1 | J3: -1 | K3: 1 | L3: 1 | M3: 2 | N3: 1
A4: 1916 | B4: 3 | C4: 4 | D4: 6.1 | E4: 6 | F4: 5.9 | G4: 6.9 | H4: 6.9 | I4: 7.9 | J4: 9.9 | K4: 10.8 | L4: 11.7 | M4: 12.6 | N4: 7.9
A5: 1917 | B5: 12.5 | C5: 15.4 | D5: 14.3 | E5: 18.9 | F5: 19.6 | G5: 20.4 | H5: 18.5 | I5: 19.3 | J5: 19.8 | K5: 19.5 | L5: 17.4 | M5: 18.1 | N5: 17.4
A6: 1918 | B6: 19.7 | C6: 17.5 | D6: 16.7 | E6: 12.7 | F6: 13.3 | G6: 13.1 | H6: 18 | I6: 18.5 | J6: 18 | K6: 18.5 | L6: 20.7 | M6: 20.4 | N6: 18
A7: 1919 | B7: 17.9 | C7: 14.9 | D7: 17.1 | E7: 17.6 | F7: 16.6 | G7: 15 | H7: 15.2 | I7: 14.9 | J7: 13.4 | K7: 13.1 | L7: 13.5 | M7: 14.5 | N7: 14.6
A8: 1920 | B8: 17 | C8: 20.4 | D8: 20.1 | E8: 21.6 | F8: 21.9 | G8: 23.7 | H8: 19.5 | I8: 14.7 | J8: 12.4 | K8: 9.9 | L8: 7 | M8: 2.6 | N8: 15.6
A9: 1921 | B9: -1.6 | C9: -5.6 | D9: -7.1 | E9: -10.8 | F9: -14.1 | G9: -15.8 | H9: -14.9 | I9: -12.8 | J9: -12.5 | K9: -12.1 | L9: -12.1 | M9: -10.8 | N9: -10.5
A10: 1922 | B10: -11.1 | C10: -8.2 | D10: -8.7 | E10: -7.7 | F10: -5.6 | G10: -5.1 | H10: -5.1 | I10: -6.2 | J10: -5.1 | K10: -4.6 | L10: -3.4 | M10: -2.3 | N10: -6.1
A11: 1923 | B11: -0.6 | C11: -0.6 | D11: 0.6 | E11: 1.2 | F11: 1.2 | G11: 1.8 | H11: 2.4 | I11: 3 | J11: 3.6 | K11: 3.6 | L11: 3 | M11: 2.4 | N11: 1.8
A12: 1924 | B12: 3 | C12: 2.4 | D12: 1.8 | E12: 0.6 | F12: 0.6 | G12: 0 | H12: -0.6 | I12: -0.6 | J12: -0.6 | K12: -0.6 | L12: -0.6 | M12: 0 | N12: 0
A13: 1925 | B13: 0 | C13: 0 | D13: 1.2 | E13: 1.2 | F13: 1.8 | G13: 2.9 | H13: 3.5 | I13: 4.1 | J13: 3.5 | K13: 2.9 | L13: 4.7 | M13: 3.5 | N13: 2.3
... A111: 2023 | B111: 6.4 | C111: 6 | D111: 5 | E111: 4.9 | F111: 4 | G111: 3 | H111: 3.2 | I111: 3.7 | J111: 3.7 | K111: 3.2 | L111: 3.1 | M111: 3.4 | N111: 4.1
